trial_project/__init__.py
trial_project/calculator.py
trial_project/cli.py
trial_project/trial_project.py
trial_project-0.0.5.dist-info/AUTHORS.rst
trial_project-0.0.5.dist-info/LICENSE
trial_project-0.0.5.dist-info/METADATA
trial_project-0.0.5.dist-info/WHEEL
trial_project-0.0.5.dist-info/entry_points.txt
trial_project-0.0.5.dist-info/top_level.txt
trial_project-0.0.5.dist-info/RECORD
