Metadata-Version: 2.1
Name: trial-project
Version: 0.0.5
Summary: Testing of packagage building and uploading.
Home-page: https://github.com/axelschmidt91/trial_project
Author: Axel Schmidt
Author-email: schmidt.axel.91@gmail.com
License: MIT license
Keywords: trial_project
Platform: UNKNOWN
Classifier: Development Status :: 2 - Pre-Alpha
Classifier: Intended Audience :: Developers
Classifier: License :: OSI Approved :: MIT License
Classifier: Natural Language :: English
Classifier: Programming Language :: Python :: 3
Classifier: Programming Language :: Python :: 3.6
Classifier: Programming Language :: Python :: 3.7
Classifier: Programming Language :: Python :: 3.8
Requires-Python: >=3.5
Requires-Dist: Click (>=7.0)
Requires-Dist: sphinx-glpi-theme (>=0.3)
